[{"name":"Minerit","_id":"515971d0a9aa2ddb6200000b","books":["515971d0a9aa2ddb62000005"]},{"name":"Gastronomie","_id":"515971d0a9aa2ddb62000010","books":["515971d0a9aa2ddb6200000c"]},{"name":"Beletristica si critica","_id":"515971d0a9aa2ddb62000015","books":["515971d0a9aa2ddb62000011"]},{"name":"Literatura engleza","_id":"515971d0a9aa2ddb6200001a","books":["515971d0a9aa2ddb62000016"]},{"name":"Eseuri","_id":"515971d1a9aa2ddb6200001f","books":["515971d0a9aa2ddb6200001b"]},{"name":"Arhitectura - Design","_id":"515971d1a9aa2ddb62000026","books":["515971d1a9aa2ddb62000020"]},{"name":"Bibliografie scolara","_id":"515971d1a9aa2ddb6200002b","books":["515971d1a9aa2ddb62000027"]},{"name":"Best - seller","_id":"515971d1a9aa2ddb62000030","books":["515971d1a9aa2ddb6200002c"]},{"name":"Literatura romana","_id":"515971d1a9aa2ddb62000035","books":["515971d1a9aa2ddb62000031"]},{"name":"Literatura romana","_id":"515971d1a9aa2ddb6200003a","books":["515971d1a9aa2ddb62000036"]},{"name":"Beletristica si critica","_id":"515971d1a9aa2ddb6200003f","books":["515971d1a9aa2ddb6200003b"]},{"name":"Carti - cadou","_id":"515971d1a9aa2ddb62000044","books":["515971d1a9aa2ddb62000040"]},{"name":"Science-Fiction","_id":"515971d1a9aa2ddb62000049","books":["515971d1a9aa2ddb62000045"]},{"name":"Beletristica si critica","_id":"515971d1a9aa2ddb6200004e","books":["515971d1a9aa2ddb6200004a"]},{"name":"Literatura spaniola","_id":"515971d2a9aa2ddb62000053","books":["515971d1a9aa2ddb6200004f"]},{"name":"Beletristica si critica","_id":"515971d2a9aa2ddb62000058","books":["515971d2a9aa2ddb62000054"]},{"name":"Beletristica si critica","_id":"515971d2a9aa2ddb6200005e","books":["515971d2a9aa2ddb62000059"]},{"name":"Best - seller","_id":"515971d2a9aa2ddb62000063","books":["515971d2a9aa2ddb6200005f"]},{"name":"Carti pentru copii","_id":"515971d2a9aa2ddb62000068","books":["515971d2a9aa2ddb62000064"]},{"name":"Povesti de neuitat","_id":"515971d2a9aa2ddb6200006d","books":["515971d2a9aa2ddb62000069"]},{"name":"Ilustrate / Benzi desenate","_id":"515971d2a9aa2ddb62000072","books":["515971d2a9aa2ddb6200006e"]},{"name":"Ilustrate / Benzi desenate","_id":"515971d2a9aa2ddb62000077","books":["515971d2a9aa2ddb62000073"]},{"name":"Bibliografie scolara","_id":"515971d2a9aa2ddb6200007c","books":["515971d2a9aa2ddb62000078"]},{"name":"Bibliografie scolara","_id":"515971d2a9aa2ddb62000081","books":["515971d2a9aa2ddb6200007d"]},{"name":"Povesti de neuitat","_id":"515971d2a9aa2ddb62000086","books":["515971d2a9aa2ddb62000082"]},{"name":"Ilustrate / Benzi desenate","_id":"515971d3a9aa2ddb6200008b","books":["515971d2a9aa2ddb62000087"]},{"name":"Ilustrate / Benzi desenate","_id":"515971d3a9aa2ddb62000090","books":["515971d3a9aa2ddb6200008c"]},{"name":"Carti pentru copii","_id":"515971d3a9aa2ddb62000095","books":["515971d3a9aa2ddb62000091"]},{"name":"Invatamant - Educatie","_id":"515971d3a9aa2ddb6200009c","books":["515971d3a9aa2ddb62000098"]},{"name":"Povesti de neuitat","_id":"515971d3a9aa2ddb620000a1","books":["515971d3a9aa2ddb6200009d"]},{"name":"Carti pentru copii","_id":"515971d3a9aa2ddb620000a6","books":["515971d3a9aa2ddb620000a2"]},{"name":"Ilustrate / Benzi desenate","_id":"515971d3a9aa2ddb620000ab","books":["515971d3a9aa2ddb620000a7"]},{"name":"Carti pentru copii","_id":"515971d3a9aa2ddb620000b0","books":["515971d3a9aa2ddb620000ac"]},{"name":"Carti pentru copii","_id":"515971d3a9aa2ddb620000b5","books":["515971d3a9aa2ddb620000b1"]},{"name":"Roman istoric","_id":"515971d3a9aa2ddb620000ba","books":["515971d3a9aa2ddb620000b6"]},{"name":"Literatura","_id":"515971d3a9aa2ddb620000bf","books":["515971d3a9aa2ddb620000bb"]},{"name":"Diverse","_id":"515971d3a9aa2ddb620000c4","books":["515971d3a9aa2ddb620000c0"]},{"name":"Carti pentru copii","_id":"515971d4a9aa2ddb620000c9","books":["515971d3a9aa2ddb620000c5"]},{"name":"Beletristica si critica","_id":"515971d4a9aa2ddb620000ce","books":["515971d4a9aa2ddb620000ca"]},{"name":"Beletristica si critica","_id":"515971d4a9aa2ddb620000d3","books":["515971d4a9aa2ddb620000cf"]},{"name":"Publicistica / Reportaje / Interviuri","_id":"515971d4a9aa2ddb620000d8","books":["515971d4a9aa2ddb620000d4"]},{"name":"Poezie","_id":"515971d4a9aa2ddb620000dd","books":["515971d4a9aa2ddb620000d9"]},{"name":"Biografii - Memorialistica","_id":"515971d4a9aa2ddb620000e2","books":["515971d4a9aa2ddb620000de"]},{"name":"Literatura clasica","_id":"515971d4a9aa2ddb620000e7","books":["515971d4a9aa2ddb620000e3"]},{"name":"Roman romanesc","_id":"515971d4a9aa2ddb620000ec","books":["515971d4a9aa2ddb620000e8"]},{"name":"Globalizare","_id":"515971d4a9aa2ddb620000f1","books":["515971d4a9aa2ddb620000ed"]},{"name":"Beletristica si critica","_id":"515971d4a9aa2ddb620000f6","books":["515971d4a9aa2ddb620000f2"]},{"name":"Beletristica si critica","_id":"515971d5a9aa2ddb620000fb","books":["515971d4a9aa2ddb620000f7"]},{"name":"Roman romanesc","_id":"515971d5a9aa2ddb62000100","books":["515971d5a9aa2ddb620000fc"]},{"name":"Beletristica si critica","_id":"515971d5a9aa2ddb62000105","books":["515971d5a9aa2ddb62000101"]},{"name":"Beletristica si critica","_id":"515971d5a9aa2ddb6200010a","books":["515971d5a9aa2ddb62000106"]},{"name":"Jurnale/Corespondenta","_id":"515971d5a9aa2ddb6200010f","books":["515971d5a9aa2ddb6200010b"]},{"name":"Beletristica si critica","_id":"515971d5a9aa2ddb62000114","books":["515971d5a9aa2ddb62000110"]},{"name":"Ortodoxie","_id":"515971d5a9aa2ddb6200011b","books":["515971d5a9aa2ddb62000115"]},{"name":"Beletristica si critica","_id":"515971d5a9aa2ddb62000120","books":["515971d5a9aa2ddb6200011c"]},{"name":"Aviatie / Astronautica","_id":"515971d5a9aa2ddb62000125","books":["515971d5a9aa2ddb62000121"]},{"name":"Literatura","_id":"515971d5a9aa2ddb6200012a","books":["515971d5a9aa2ddb62000126"]},{"name":"Carti pentru copii","_id":"515971d6a9aa2ddb62000135","books":["515971d5a9aa2ddb62000131"]},{"name":"Bibliografie scolara","_id":"515971d6a9aa2ddb6200013a","books":["515971d6a9aa2ddb62000136"]},{"name":"Literatura romana","_id":"515971d6a9aa2ddb6200013f","books":["515971d6a9aa2ddb6200013b"]},{"name":"Istoria romanilor","_id":"515971d6a9aa2ddb62000144","books":["515971d6a9aa2ddb62000140"]},{"name":"Ortodoxie","_id":"515971d6a9aa2ddb62000149","books":["515971d6a9aa2ddb62000145"]},{"name":"Gradinita","_id":"515971d6a9aa2ddb6200014e","books":["515971d6a9aa2ddb6200014a"]},{"name":"Literatura adolescenti","_id":"515971d6a9aa2ddb62000153","books":["515971d6a9aa2ddb6200014f"]},{"name":"Economie politica","_id":"515971d6a9aa2ddb62000158","books":["515971d6a9aa2ddb62000154"]},{"name":"Carti politiste","_id":"515971d6a9aa2ddb6200015d","books":["515971d6a9aa2ddb62000159"]},{"name":"Afaceri","_id":"515971d6a9aa2ddb62000162","books":["515971d6a9aa2ddb6200015e"]},{"name":"Sociologie","_id":"515971d6a9aa2ddb62000167","books":["515971d6a9aa2ddb62000163"]},{"name":"Schite / Nuvele si povestiri","_id":"515971d6a9aa2ddb6200016c","books":["515971d6a9aa2ddb62000168"]},{"name":"Proza contemporana","_id":"515971d7a9aa2ddb62000171","books":["515971d7a9aa2ddb6200016d"]},{"name":"Beletristica si critica","_id":"515971d7a9aa2ddb62000176","books":["515971d7a9aa2ddb62000172"]},{"name":"Istoria literaturii romane","_id":"515971d7a9aa2ddb6200017b","books":["515971d7a9aa2ddb62000177"]},{"name":"Fantasy","_id":"515971d7a9aa2ddb62000180","books":["515971d7a9aa2ddb6200017c"]},{"name":"Psihologie","_id":"515971d7a9aa2ddb62000185","books":["515971d7a9aa2ddb62000181"]},{"name":"Science-Fiction","_id":"515971d7a9aa2ddb6200018a","books":["515971d7a9aa2ddb62000186"]},{"name":"Poezie","_id":"515971d7a9aa2ddb6200018f","books":["515971d7a9aa2ddb6200018b"]},{"name":"Mituri si legende","_id":"515971d7a9aa2ddb62000194","books":["515971d7a9aa2ddb62000190"]},{"name":"Mitologie","_id":"515971d7a9aa2ddb62000199","books":["515971d7a9aa2ddb62000195"]},{"name":"Science-Fiction","_id":"515971d8a9aa2ddb6200019e","books":["515971d7a9aa2ddb6200019a"]},{"name":"Sociologie","_id":"515971d8a9aa2ddb620001a3","books":["515971d8a9aa2ddb6200019f"]},{"name":"Roman strain","_id":"515971d8a9aa2ddb620001a8","books":["515971d8a9aa2ddb620001a4"]},{"name":"Beletristica si critica","_id":"515971d8a9aa2ddb620001ae","books":["515971d8a9aa2ddb620001a9"]},{"name":"Horror","_id":"515971d8a9aa2ddb620001b3","books":["515971d8a9aa2ddb620001af"]},{"name":"Literatura romana","_id":"515971d8a9aa2ddb620001b8","books":["515971d8a9aa2ddb620001b4"]},{"name":"Dezvoltare personala","_id":"515971d8a9aa2ddb620001bd","books":["515971d8a9aa2ddb620001b9"]},{"name":"Poezie","_id":"515971d8a9aa2ddb620001c2","books":["515971d8a9aa2ddb620001be"]},{"name":"Ideologii / Partide politice","_id":"515971d8a9aa2ddb620001c7","books":["515971d8a9aa2ddb620001c3"]},{"name":"Roman istoric","_id":"515971d8a9aa2ddb620001d2","books":["515971d8a9aa2ddb620001ce"]},{"name":"Best - seller","_id":"515971d8a9aa2ddb620001d7","books":["515971d8a9aa2ddb620001d3"]},{"name":"Dreptul muncii","_id":"515971d9a9aa2ddb620001dc","books":["515971d8a9aa2ddb620001d8"]},{"name":"Protectia mediului","_id":"515971d9a9aa2ddb620001e1","books":["515971d9a9aa2ddb620001dd"]},{"name":"Carti pentru copii","_id":"515971d9a9aa2ddb620001e6","books":["515971d9a9aa2ddb620001e2"]},{"name":"Ilustrate / Benzi desenate","_id":"515971d9a9aa2ddb620001eb","books":["515971d9a9aa2ddb620001e7"]},{"name":"Literatura romana","_id":"515971d9a9aa2ddb620001f0","books":["515971d9a9aa2ddb620001ec"]},{"name":"Carti pentru copii","_id":"515971d9a9aa2ddb620001f5","books":["515971d9a9aa2ddb620001f1"]},{"name":"Istoria romanilor","_id":"515971d9a9aa2ddb620001fb","books":["515971d9a9aa2ddb620001f6"]},{"name":"Beletristica si critica","_id":"515971d9a9aa2ddb62000200","books":["515971d9a9aa2ddb620001fc"]},{"name":"Poezie","_id":"515971d9a9aa2ddb62000205","books":["515971d9a9aa2ddb62000201"]},{"name":"Beletristica si critica","_id":"515971d9a9aa2ddb6200020a","books":["515971d9a9aa2ddb62000206"]},{"name":"Istoria Europei","_id":"515971d9a9aa2ddb6200020f","books":["515971d9a9aa2ddb6200020b"]},{"name":"Roman romanesc","_id":"515971d9a9aa2ddb62000214","books":["515971d9a9aa2ddb62000210"]},{"name":"Beletristica si critica","_id":"515971d9a9aa2ddb62000219","books":["515971d9a9aa2ddb62000215"]},{"name":"Stiinta si Tehnica","_id":"515971d9a9aa2ddb6200021e","books":["515971d9a9aa2ddb6200021a"]},{"name":"Crestinism","_id":"515971d9a9aa2ddb62000223","books":["515971d9a9aa2ddb6200021f"]},{"name":"Calatorii","_id":"515971daa9aa2ddb62000228","books":["515971d9a9aa2ddb62000224"]},{"name":"Beletristica si critica","_id":"515971daa9aa2ddb6200022d","books":["515971daa9aa2ddb62000229"]},{"name":"Limbi straine","_id":"515971daa9aa2ddb62000232","books":["515971daa9aa2ddb6200022e"]},{"name":"Beletristica si critica","_id":"515971daa9aa2ddb62000237","books":["515971daa9aa2ddb62000233"]},{"name":"Beletristica si critica","_id":"515971daa9aa2ddb6200023c","books":["515971daa9aa2ddb62000238"]},{"name":"Beletristica si critica","_id":"515971daa9aa2ddb62000241","books":["515971daa9aa2ddb6200023d"]},{"name":"Beletristica si critica","_id":"515971daa9aa2ddb62000246","books":["515971daa9aa2ddb62000242"]},{"name":"Roman romanesc","_id":"515971daa9aa2ddb6200024b","books":["515971daa9aa2ddb62000247"]},{"name":"Carti politiste","_id":"515971daa9aa2ddb62000250","books":["515971daa9aa2ddb6200024c"]},{"name":"Carti - cadou","_id":"515971daa9aa2ddb62000255","books":["515971daa9aa2ddb62000251"]},{"name":"Literatura Nord-Americana","_id":"515971daa9aa2ddb6200025a","books":["515971daa9aa2ddb62000256"]},{"name":"Jurnale/Corespondenta","_id":"515971dba9aa2ddb6200025f","books":["515971daa9aa2ddb6200025b"]},{"name":"Calatorii","_id":"515971dba9aa2ddb62000264","books":["515971dba9aa2ddb62000260"]},{"name":"Roman romanesc","_id":"515971dba9aa2ddb6200026f","books":["515971dba9aa2ddb6200026b"]},{"name":"Beletristica si critica","_id":"515971dba9aa2ddb62000274","books":["515971dba9aa2ddb62000270"]},{"name":"Poezie","_id":"515971dba9aa2ddb62000279","books":["515971dba9aa2ddb62000275"]},{"name":"Literatura romana","_id":"515971dba9aa2ddb6200027e","books":["515971dba9aa2ddb6200027a"]},{"name":"Ciclul primar","_id":"515971dba9aa2ddb62000283","books":["515971dba9aa2ddb6200027f"]},{"name":"Literatura romana","_id":"515971dba9aa2ddb62000288","books":["515971dba9aa2ddb62000284"]},{"name":"Beletristica si critica","_id":"515971dca9aa2ddb6200028d","books":["515971dba9aa2ddb62000289"]},{"name":"Beletristica si critica","_id":"515971dca9aa2ddb62000292","books":["515971dca9aa2ddb6200028e"]},{"name":"Jurnale/Corespondenta","_id":"515971dca9aa2ddb62000297","books":["515971dca9aa2ddb62000293"]},{"name":"Beletristica si critica","_id":"515971dca9aa2ddb6200029c","books":["515971dca9aa2ddb62000298"]},{"name":"Teatru","_id":"515971dca9aa2ddb620002a1","books":["515971dca9aa2ddb6200029d"]},{"name":"Proza contemporana","_id":"515971dca9aa2ddb620002a6","books":["515971dca9aa2ddb620002a2"]},{"name":"Roman romanesc","_id":"515971dca9aa2ddb620002ac","books":["515971dca9aa2ddb620002a7"]},{"name":"Literatura Nord-Americana","_id":"515971dca9aa2ddb620002b1","books":["515971dca9aa2ddb620002ad"]},{"name":"Poezie","_id":"515971dca9aa2ddb620002b6","books":["515971dca9aa2ddb620002b2"]},{"name":"Metodologie / Pedagogie","_id":"515971dca9aa2ddb620002bb","books":["515971dca9aa2ddb620002b7"]},{"name":"Beletristica si critica","_id":"515971dca9aa2ddb620002c0","books":["515971dca9aa2ddb620002bc"]},{"name":"Beletristica si critica","_id":"515971dda9aa2ddb620002c5","books":["515971dca9aa2ddb620002c1"]},{"name":"Carti de dragoste","_id":"515971dda9aa2ddb620002ca","books":["515971dda9aa2ddb620002c6"]},{"name":"Literatura italiana","_id":"515971dda9aa2ddb620002cf","books":["515971dda9aa2ddb620002cb"]},{"name":"Ilustrate / Benzi desenate","_id":"515971dda9aa2ddb620002d4","books":["515971dda9aa2ddb620002d0"]},{"name":"Istoria Europei","_id":"515971dda9aa2ddb620002d9","books":["515971dda9aa2ddb620002d5"]},{"name":"Beletristica si critica","_id":"515971dda9aa2ddb620002de","books":["515971dda9aa2ddb620002da"]},{"name":"Beletristica si critica","_id":"515971dda9aa2ddb620002e3","books":["515971dda9aa2ddb620002df"]},{"name":"Gradinita","_id":"515971dda9aa2ddb620002e8","books":["515971dda9aa2ddb620002e4"]},{"name":"Beletristica si critica","_id":"515971dda9aa2ddb620002ec","books":["515971dda9aa2ddb620002e9"]},{"name":"Roman romanesc","_id":"515971dda9aa2ddb620002f1","books":["515971dda9aa2ddb620002ed"]},{"name":"Politica","_id":"515971dda9aa2ddb620002f6","books":["515971dda9aa2ddb620002f2"]},{"name":"Literatura germana","_id":"515971dda9aa2ddb620002fb","books":["515971dda9aa2ddb620002f7"]},{"name":"Carti pentru copii","_id":"515971dda9aa2ddb62000304","books":["515971dda9aa2ddb62000300"]},{"name":"Arhitectura - Design","_id":"515971dea9aa2ddb62000309","books":["515971dda9aa2ddb62000305"]},{"name":"Bibliografie scolara","_id":"515971dea9aa2ddb6200030e","books":["515971dea9aa2ddb6200030a"]},{"name":"Clasici romani","_id":"515971dea9aa2ddb62000313","books":["515971dea9aa2ddb6200030f"]},{"name":"Calatorii","_id":"515971dea9aa2ddb62000318","books":["515971dea9aa2ddb62000314"]},{"name":"Stiinta si Tehnica","_id":"515971dea9aa2ddb6200031d","books":["515971dea9aa2ddb62000319"]},{"name":"Beletristica si critica","_id":"515971dea9aa2ddb62000322","books":["515971dea9aa2ddb6200031e"]},{"name":"Beletristica si critica","_id":"515971dea9aa2ddb62000327","books":["515971dea9aa2ddb62000323"]},{"name":"Beletristica si critica","_id":"515971dea9aa2ddb6200032c","books":["515971dea9aa2ddb62000328"]},{"name":"Economie","_id":"515971dea9aa2ddb62000331","books":["515971dea9aa2ddb6200032d"]},{"name":"Beletristica si critica","_id":"515971dea9aa2ddb62000336","books":["515971dea9aa2ddb62000332"]},{"name":"Enciclopedii","_id":"515971dea9aa2ddb6200033b","books":["515971dea9aa2ddb62000337"]},{"name":"Carti pentru copii","_id":"515971dfa9aa2ddb62000340","books":["515971dea9aa2ddb6200033c"]},{"name":"Carti pentru copii","_id":"515971dfa9aa2ddb62000347","books":["515971dfa9aa2ddb62000341"]},{"name":"2-6 ani","_id":"515971dfa9aa2ddb6200034c","books":["515971dfa9aa2ddb62000348"]},{"name":"E-learning","_id":"515971dfa9aa2ddb62000351","books":["515971dfa9aa2ddb6200034d"]},{"name":"Animale de casa","_id":"515971dfa9aa2ddb62000356","books":["515971dfa9aa2ddb62000352"]},{"name":"Bibliografie scolara","_id":"515971dfa9aa2ddb6200035b","books":["515971dfa9aa2ddb62000357"]},{"name":"Beletristica si critica","_id":"515971dfa9aa2ddb62000360","books":["515971dfa9aa2ddb6200035c"]},{"name":"Gradinita","_id":"515971dfa9aa2ddb62000365","books":["515971dfa9aa2ddb62000361"]},{"name":"Clasa I","_id":"515971dfa9aa2ddb6200036a","books":["515971dfa9aa2ddb62000366"]},{"name":"Zootehnie","_id":"515971dfa9aa2ddb62000372","books":["515971dfa9aa2ddb6200036b"]},{"name":"Fictiune","_id":"515971dfa9aa2ddb62000377","books":["515971dfa9aa2ddb62000373"]},{"name":"Roman romanesc","_id":"515971dfa9aa2ddb6200037c","books":["515971dfa9aa2ddb62000378"]},{"name":"Beletristica si critica","_id":"515971e0a9aa2ddb62000381","books":["515971dfa9aa2ddb6200037d"]},{"name":"Beletristica si critica","_id":"515971e0a9aa2ddb62000386","books":["515971e0a9aa2ddb62000382"]},{"name":"Science-Fiction","_id":"515971e0a9aa2ddb6200038b","books":["515971e0a9aa2ddb62000387"]},{"name":"Literatura rusa","_id":"515971e0a9aa2ddb62000390","books":["515971e0a9aa2ddb6200038c"]},{"name":"Beletristica si critica","_id":"515971e0a9aa2ddb62000395","books":["515971e0a9aa2ddb62000391"]},{"name":"Beletristica si critica","_id":"515971e0a9aa2ddb6200039a","books":["515971e0a9aa2ddb62000396"]},{"name":"Literatura","_id":"515971e0a9aa2ddb6200039f","books":["515971e0a9aa2ddb6200039b"]},{"name":"Carti de dragoste","_id":"515971e0a9aa2ddb620003a4","books":["515971e0a9aa2ddb620003a0"]},{"name":"Literatura","_id":"515971e0a9aa2ddb620003a9","books":["515971e0a9aa2ddb620003a5"]},{"name":"Turism","_id":"515971e0a9aa2ddb620003ae","books":["515971e0a9aa2ddb620003aa"]},{"name":"Carti pentru copii","_id":"515971e0a9aa2ddb620003b3","books":["515971e0a9aa2ddb620003af"]},{"name":"Crestinism","_id":"515971e0a9aa2ddb620003b8","books":["515971e0a9aa2ddb620003b4"]},{"name":"Beletristica","_id":"515971e0a9aa2ddb620003bd","books":["515971e0a9aa2ddb620003b9"]}]